altendpy/__init__.py
altendpy/_version.py
altendpy/compat.py
altendpy/misc.py
altendpy/processtemplates.py
altendpy/timeit.py
altendpy/cli/__init__.py
altendpy/cli/misc.py
altendpy/tests/__init__.py
altendpy/tests/common.py
altendpy/tests/test_misc.py
altendpy/tests/test_timeit.py
altendpy-0.0.21.dist-info/METADATA
altendpy-0.0.21.dist-info/WHEEL
altendpy-0.0.21.dist-info/entry_points.txt
altendpy-0.0.21.dist-info/top_level.txt
altendpy-0.0.21.dist-info/RECORD
