Metadata-Version: 2.1
Name: altendpy
Version: 0.0.21
Summary: Extras for working with Python.
Home-page: https://github.com/altendky/altendpy
Author: Kyle Altendorf
Author-email: sda@fstab.net
License: UNKNOWN
Platform: UNKNOWN
Classifier: Development Status :: 3 - Alpha
Classifier: Intended Audience :: Developers
Classifier: Programming Language :: Python :: 3
Classifier: Programming Language :: Python :: 3.5
Classifier: Programming Language :: Python :: 3.6
Classifier: Programming Language :: Python :: 3.7
Requires-Python: >=3.5
Requires-Dist: attrs
Requires-Dist: jinja2
Provides-Extra: dev
Requires-Dist: gitignoreio ; extra == 'dev'
Provides-Extra: test
Requires-Dist: codecov ; extra == 'test'
Requires-Dist: pytest ; extra == 'test'
Requires-Dist: pytest-cov ; extra == 'test'
Requires-Dist: tox ; extra == 'test'
